pychecksumcache/__init__.py
pychecksumcache/py.typed
pychecksumcache/pychecksumcache.py
pychecksumcache-1.1.0.dist-info/METADATA
pychecksumcache-1.1.0.dist-info/WHEEL
pychecksumcache-1.1.0.dist-info/entry_points.txt
pychecksumcache-1.1.0.dist-info/licenses/LICENSE
pychecksumcache-1.1.0.dist-info/RECORD
