Metadata-Version: 2.4
Name: pychecksumcache
Version: 1.1.0
Summary: A lightweight Python library that uses MD5 checksums to track file changes and execute code only when files have been modified. PyChecksumCache maintains a persistent cache of file checksums, making it ideal for build systems, asset processors, incremental compilers, and any tools that need efficient change detection.
Project-URL: homepage, https://github.com/sylvainmouquet/pychecksumcache
Project-URL: documentation, https://github.com/sylvainmouquet/pychecksumcache
Project-URL: repository, https://github.com/sylvainmouquet/pychecksumcache
Project-URL: changelog, https://github.com/sylvainmouquet/pychecksumcache/releases
Author-email: Sylvain Mouquet <sylvain.mouquet@gmail.com>
License: MIT
License-File: LICENSE
Keywords: async,automation,build-tools,cache,change-detection,checksum,developer-tools,development-tools,digest,file-monitoring,hash,incremental-processing,md5,optimization,python,python3
Classifier: Development Status :: 5 - Production/Stable
Classifier: Framework :: Pytest
Classifier: Intended Audience :: Developers
Classifier: License :: OSI Approved :: MIT License
Classifier: Programming Language :: Python
Classifier: Programming Language :: Python :: 3
Classifier: Programming Language :: Python :: 3.10
Classifier: Programming Language :: Python :: 3.11
Classifier: Programming Language :: Python :: 3.12
Classifier: Programming Language :: Python :: 3.13
Classifier: Topic :: Software Development :: Libraries :: Python Modules
Requires-Python: >=3.10
